{
    "player": {
        "name": "Jude Bellingham",
        "slug": "jude-bellingham",
        "shortName": "J. Bellingham",
        "team": {
            "name": "Real Madrid",
            "slug": "real-madrid",
            "shortName": "Real Madrid",
            "gender": "M",
            "sport": {
                "name": "Football",
                "slug": "football",
                "id": 1
            },
            "tournament": {
                "name": "LaLiga",
                "slug": "laliga",
                "category": {
                    "name": "Spain",
                    "slug": "spain",
                    "sport": {
                        "name": "Football",
                        "slug": "football",
                        "id": 1
                    },
                    "id": 32,
                    "flag": "spain",
                    "alpha2": "ES"
                },
                "uniqueTournament": {
                    "name": "LaLiga",
                    "slug": "laliga",
                    "primaryColorHex": "#2f4a89",
                    "secondaryColorHex": "#f4a32e",
                    "category": {
                        "name": "Spain",
                        "slug": "spain",
                        "sport": {
                            "name": "Football",
                            "slug": "football",
                            "id": 1
                        },
                        "id": 32,
                        "flag": "spain",
                        "alpha2": "ES"
                    },
                    "userCount": 862312,
                    "id": 8,
                    "country": {},
                    "displayInverseHomeAwayTeams": false
                },
                "priority": 588,
                "id": 36
            },
            "primaryUniqueTournament": {
                "name": "LaLiga",
                "slug": "laliga",
                "primaryColorHex": "#2f4a89",
                "secondaryColorHex": "#f4a32e",
                "category": {
                    "name": "Spain",
                    "slug": "spain",
                    "sport": {
                        "name": "Football",
                        "slug": "football",
                        "id": 1
                    },
                    "id": 32,
                    "flag": "spain",
                    "alpha2": "ES"
                },
                "userCount": 862312,
                "id": 8,
                "country": {},
                "displayInverseHomeAwayTeams": false
            },
            "userCount": 1632559,
            "nameCode": "RMA",
            "disabled": false,
            "national": false,
            "type": 0,
            "id": 2829,
            "country": {
                "alpha2": "ES",
                "name": "Spain"
            },
            "teamColors": {
                "primary": "#ffffff",
                "secondary": "#004996",
                "text": "#004996"
            }
        },
        "position": "M",
        "jerseyNumber": "5",
        "height": 188,
        "preferredFoot": "Right",
        "retired": false,
        "userCount": 89891,
        "deceased": false,
        "id": 991011,
        "country": {
            "alpha2": "EN",
            "name": "England"
        },
        "shirtNumber": 5,
        "dateOfBirthTimestamp": 1056844800,
        "contractUntilTimestamp": 1877472000,
        "proposedMarketValue": 113000000,
        "proposedMarketValueRaw": {
            "value": 113000000,
            "currency": "EUR"
        }
    }
}